tinytoggle/__init__.py
tinytoggle-2024.7.3.dist-info/METADATA
tinytoggle-2024.7.3.dist-info/WHEEL
tinytoggle-2024.7.3.dist-info/licenses/LICENSE
tinytoggle-2024.7.3.dist-info/RECORD
