Metadata-Version: 2.3
Name: tinytoggle
Version: 2024.7.3
Summary: A tiny feature toggle module.
Project-URL: Homepage, https://github.com/trolann/tinytoggle
Project-URL: Issues, https://github.com/trolann/tinytoggle/issues
Author-email: Trevor Mathisen <trevor@mathisen.dev>
License-File: LICENSE
Classifier: License :: OSI Approved :: MIT License
Classifier: Operating System :: OS Independent
Classifier: Programming Language :: Python :: 3
Requires-Python: >=3.10
